Workbook

Sheet Expenses
B2: Theatre Production AY2526 | L2: EXPENSES
B4: TOTAL EXPENSES | C4: As of 01/06/2026 | L4: Actual
C5: Order Tracking | L5: =SUM(D16,J16,D60,J60) -> 15684.2
B7: Rumors | C7: REF # | D7: PENDING CC | E7: ENC | F7: YTD | H7: Dolly West's Kitchen | I7: REF # | J7: PENDING CC | K7: ENC | L7: YTD
B8: Scenic | D8: =[1]Expenses!$D$38 -> 758.35 | E8: =[1]Expenses!$E$38 -> 52.46 | F8: =[1]Expenses!$F$38 -> 3251.05 | H8: Scenic | J8: =[2]Expenses!$D$38 -> 0 | K8: =[2]Expenses!$E$38 -> 0 | L8: =[2]Expenses!$F$38 -> 0
B9: Costumes | D9: =[1]Expenses!$J$38 -> 107.1 | E9: =[1]Expenses!$K$38 -> 0 | F9: =[1]Expenses!$L$38 -> 1596.96 | H9: Costumes | J9: =[2]Expenses!$J$38 -> 0 | K9: =[2]Expenses!$K$38 -> 84.36 | L9: =[2]Expenses!$L$38 -> 0
B10: Lighting | D10: =[1]Expenses!$D$72 -> 35.92 | E10: =[1]Expenses!$E$72 -> 0 | F10: =[1]Expenses!$F$72 -> 380.57 | H10: Lighting | J10: =[2]Expenses!$D$72 -> 0 | K10: =[2]Expenses!$E$72 -> 0 | L10: =[2]Expenses!$F$72 -> 0
B11: Sound | D11: =[1]Expenses!$J$72 -> 0 | E11: =[1]Expenses!$K$72 -> 112.48 | F11: =[1]Expenses!$L$72 -> 0 | H11: Sound | J11: =[2]Expenses!$J$72 -> 0 | K11: =[2]Expenses!$K$72 -> 0 | L11: =[2]Expenses!$L$72 -> 0
B12: Rights | D12: =[1]Expenses!$D$79 -> 0 | E12: =[1]Expenses!$E$79 -> 0 | F12: =[1]Expenses!$F$79 -> 1148.55 | H12: Rights | J12: =[2]Expenses!$D$79 -> 0 | K12: =[2]Expenses!$E$79 -> 0 | L12: =[2]Expenses!$F$79 -> 995
B13: Props | D13: =[1]Expenses!$D$88 -> 160.28 | E13: =[1]Expenses!$E$88 -> 0 | F13: =[1]Expenses!$F$88 -> 143.38 | H13: Props | J13: =[2]Expenses!$D$93 -> 0 | K13: =[2]Expenses!$E$93 -> 0 | L13: =[2]Expenses!$F$93 -> 0
B14: Miscellaneous | D14: =[1]Expenses!$J$88 -> 0 | E14: =[1]Expenses!$K$88 -> 0 | F14: =[1]Expenses!$L$88 -> 525 | H14: Miscellaneous | J14: =[2]Expenses!$J$93 -> 0 | K14: =[2]Expenses!$K$93 -> 0 | L14: =[2]Expenses!$L$93 -> 400
C15: TOTALS | D15: =SUM(D8:D14) -> 1061.65 | E15: =SUM(E8:E14) -> 164.94 | F15: =SUM(F8:F14) -> 7045.51 | I15: TOTALS | J15: =SUM(J8:J14) -> 0 | K15: =SUM(K8:K14) -> 84.36 | L15: =SUM(L8:L14) -> 1395
B16: 7248.55 | C16: TOTAL | D16: =SUM(D15:F15) -> 8272.1 | H16: 6095 | I16: ALL TOTAL | J16: =SUM(J15:L15) -> 1479.36
B18: Fall Miscellaneous | C18: REF # | D18: PENDING CC | E18: ENC | F18: YTD | H18: Spring Miscellaneous | I18: REF # | J18: PENDING CC | K18: ENC | L18: YTD
B19: Lapels Dry Cleaning | C19: EP013519 | E19: 400 | H19: Speaker Correction | L19: 749.99
B20: Lapels Dry Cleaning | C20: EP010561 | E20: 400 | H20: Propared | L20: 1200
B21: B & H Foto & Electronics Corp. (Video) | C21: EP016353 | F21: 226.37 | H21: Lightwright License | L21: 400
B22: CaseLabelUsa | C22: J0179555 | F22: 194.4 | H22: Guest Artist Overage | L22: 138.79
B23: Department AMEX (October) | C23: EC000111 | D23: =IFERROR(__xludf.DUMMYFUNCTION("IMPORTRANGE(""https://docs.google.com/spreadsheets/d/1sZRbdRRzTpKWFUnhV1wm2WFcpJ4ShN_vLQ64iyUnRuY/edit?gid=962100944#gid=962100944"",""Credit Card Purchases!J11"")"),"#REF!") -> #REF! | H23: Theatre Awards | L23: 300
B24: B & H Foto & Electronics Corp. (Sound) | C24: EP017361 | F24: 653.46
B25: B & H Foto & Electronics Corp. (Sound) | C25: EP017726 | F25: 1499.98
B26: B & H Foto & Electronics Corp. (Sound) | C26: EP017591 | F26: 59.99
B27: B & H Foto & Electronics Corp. (Sound) | C27: EP017693 | F27: 28.96
B28: Amazon Business, Inc | C28: EP017855 | E28: 83.46
B29: B & H Foto & Electronics Corp. (Sound) | C29: EP017852 | F29: 347.33
B30: B & H Foto & Electronics Corp. (Sound) | C30: EP017726 | F30: -749.99 | G30: ?
C59: TOTALS | D59: =SUM(D19:D58) -> 0 | E59: =SUM(E19:E58) -> 883.46 | F59: =SUM(F19:F58) -> 2260.5 | I59: TOTALS | J59: =SUM(J19:J58) -> 0 | K59: =SUM(K19:K58) -> 0 | L59: =SUM(L19:L58) -> 2788.78
B60: 1250 | C60: TOTAL | D60: =SUM(D59:F59) -> 3143.96 | H60: 1250 | I60: TOTAL | J60: =SUM(J59:L59) -> 2788.78

Sheet Income
B2: =Expenses!B2 -> Theatre Production AY2526 | G2: INCOME
B4: TOTAL INCOME | C4: =Expenses!C4 -> As of 01/06/2026 | G4: Actual
C5: =Expenses!C5 -> Order Tracking | G5: =SUM(Income!$G$16,Income!$G$23,Income!$G$34) -> 6694.78
B7: LUDUS CHECKS
B8: LINE ITEM | F8: REF # | G8: INCOME
B9: Ludus Check for July | F9: F0077302 | G9: 8.64
B10: Ludus Check for October | F10: F0078250 | G10: 60.71
B11: Ludus Check Rumors | F11: F0078503 | G11: 5988.1
B12: Ludus Check from Donations | F12: F0078679 | G12: 637.33
B16: Total | G16: =SUBTOTAL(109,Income!$G$9:$G$15) -> 6694.78
B18: MISC DONATIONS
B19: LINE ITEM | F19: REF # | G19: INCOME
B23: Total | G23: =SUBTOTAL(109,Income!$G$20:$G$22) -> 0
B25: MISC INCOME
B26: LINE ITEM | F26: REF # | G26: INCOME
B34: TOTAL | G34: =SUBTOTAL(109,Income!$G$27:$G$33) -> 0

Sheet Budget Summary
A1: 22
B2: =Expenses!B2 -> Theatre Production AY2526 | G2: BUDGET
B4: BUDGET SUMMARY | C4: =Expenses!C4 -> As of 01/06/2026
C5: =Expenses!C5 -> Order Tracking | J5: Total Budget (Revenue) | K5: =SUM(D8,D12) -> 24311.25
J6: Total Spent (Expenses) | K6: =-SUM(D9:D11, D13) -> 17684.2
B7: Total | D7: Actual | J7: Spent Slice (green) | K7: =IF(K6 > 0, MIN(K6, K5), 0) -> 17684.2
B8: Adjusted Budget | D8: 17616.47 | J8: Remaining Slice (Yellow) | K8: =IF(K5 > K6, K5 - K6, 0) -> 6627.05
B9: YTD Activity | D9: =SUM(Expenses!F15,Expenses!L15,Expenses!F59,Expenses!L59)*-1 -> -13489.79
B10: Commitments | D10: =SUM(Expenses!E15,Expenses!K15,Expenses!E59,Expenses!K59)*-1 -> -1132.76
B11: Pending CC | D11: =SUM(Expenses!D15,Expenses!J15,Expenses!D59,Expenses!J59)*-1 -> -1061.65
B12: Revenue | D12: =Income!G5 -> 6694.78
B13: Emergency Fund | D13: -2000
B14: Total budget (or loss) | D14: =SUM(D8:D13) -> 6627.05
